strotools/common/__init__.py
strotools/common/connection.py
strotools/common/util.py
strotools.common-0.0.2.dist-info/LICENSE
strotools.common-0.0.2.dist-info/METADATA
strotools.common-0.0.2.dist-info/WHEEL
strotools.common-0.0.2.dist-info/top_level.txt
strotools.common-0.0.2.dist-info/RECORD
