Metadata-Version: 2.1
Name: strotools.common
Version: 0.0.2
Summary: Strotools common packages
Home-page: https://github.com/mrstrozy/strotools.common
Author: Matthew Strozyk
Author-email: mstrozyk25@gmail.com
License: UNKNOWN
Platform: UNKNOWN
Classifier: Programming Language :: Python :: 3
Classifier: License :: OSI Approved :: MIT License
Classifier: Operating System :: OS Independent
Requires-Python: >=3.6
Requires-Dist: requests
